which_cloud/__init__.py
which_cloud/providers.py
which_cloud/whichcloud.py
which_cloud/data/data.pickle
which_cloud-1.0.2.dist-info/METADATA
which_cloud-1.0.2.dist-info/WHEEL
which_cloud-1.0.2.dist-info/top_level.txt
which_cloud-1.0.2.dist-info/RECORD
