Metadata-Version: 2.1
Name: which-cloud
Version: 1.0.2
Summary: Given an ip address, return which cloud provider it belongs to.
Home-page: https://github.com/SoundOn/which-cloud
Author: SoundOn
Author-email: dev@soundon.fm
License: MIT
Keywords: cloud ip aws gcp azure
Platform: UNKNOWN
Classifier: Development Status :: 5 - Production/Stable
Classifier: Intended Audience :: Developers
Classifier: License :: OSI Approved :: MIT License
Classifier: Programming Language :: Python
Classifier: Programming Language :: Python :: 3
Classifier: Programming Language :: Python :: 3.5
Classifier: Programming Language :: Python :: 3.6
Classifier: Programming Language :: Python :: 3.7
Classifier: Programming Language :: Python :: 3.8
Classifier: Programming Language :: Python :: 3.9
Requires-Python: >=3.5
Requires-Dist: netaddr (>=0.8.0)
